[
  {
    "content_id": 702244,
    "reference_id": 203180,
    "title": "ٱلله بصفته المحارب القدوس",
    "media_type": "Text",
    "index_reference": "ٱلله بصفته المحارب القدوس",
    "language": "arb",
    "content": "<p>المصطلح العربي <em>الجهاد،</em> المعروف الآن في اللغة الإنجليزية، يشير إلى &quot;الحرب المقدسة&quot; حيث يقاتل الرجال من أجل الله. إلا أن الكتاب المقدس يصف &quot;الحرب المقدسة&quot; بشكل مختلف. في الكتاب المقدس، الحرب المقدسة هي صراع يقاتل فيه الله من أجل شعبه بينما يثقون هم به. في هذه الحروب، يعتمد النصر على الطاعة لله، وليس على الأسلحة.</p><p>أثناء الحرب، أعلن الملك يهوشافاط ملك يهوذا صومًا، وصلى إلى الله بمرثاة (<a href=\"https://ref.ly/2Chr20:3\">2 أخبار الأيام 20:3،</a> <a href=\"https://ref.ly/2Chr20:5-2Chr20:12\">5–12</a>). تضمنت هذه الصلاة مناشدة لله، وتقديم الشكوى، والاعتراف بالثقة، وطلب المساعدة.</p><p>أظهر يهوشافاط والشعب تواضعهم بالسجود ووجوههم إلى الأرض (<a href=\"https://ref.ly/2Chr20:18\">2 أخبار الأيام 20:18</a>). من المذهل رؤية جيش يقوده جوقة تسبح لله وهم يسيرون إلى المعركة (<a href=\"https://ref.ly/2Chr20:21\">20:21</a>). فعادةً لا تكون ساحات المعارك مكانًا للعبادة والتسبيح. إلا أن العبادة تساعد الناس على فهم إرادة ٱلله وتدعوه ليُخلّص شعبه. يكافئ ٱلله الثقة به. في حالة يهوشافاط، هزم ٱلله تحالفًا كبيرًا من الأعداء دون أن تحتاج إسرائيل للقتال على الإطلاق (<a href=\"https://ref.ly/2Chr20:22-2Chr20:24\">20:22–24</a>).</p><p>يُظهر العهد الجديد الرب يسوع بصفته المحارب الجبار الذي انتصر على جميع القوى المضادة لملكوت الله (انظر <a href=\"https://ref.ly/Eph1:19-Eph1:21\">أفسس 1:19–21</a>). في النهاية، سيهزم الرب يسوع جميع الأعداء (<a href=\"https://ref.ly/1Cor15:24-1Cor15:28\">1 كورنثوس 15:24–28</a>; <a href=\"https://ref.ly/Rev19:11-Rev20:15\">رؤيا 19:11–20:15</a>). هذا الانتصار سيجعل حكم وعبادته كاملين: “<span>هَلِّلُويَا! فَإِنَّهُ قَدْ مَلَكَ ٱلرَّبُّ ٱلْإِلَهُ ٱلْقَادِرُ عَلَى كُلِّ شَيْءٍ.</span>” (<a href=\"https://ref.ly/Rev19:6\">رؤيا 19:6</a>).</p><p><u>مقاطع إضافية للدراسة</u></p><p><a href=\"https://ref.ly/Josh6:1-Josh6:20\">يشوع 6:1–20</a>; <a href=\"https://ref.ly/Josh10:7-Josh10:15\">10:7–15</a>; <a href=\"https://ref.ly/Judg7:7-Judg7:22\">قضاة 7:7–22</a>; <a href=\"https://ref.ly/2Kgs19:14-2Kgs19:37\">2 ملوك 19:14–37</a>; <a href=\"https://ref.ly/2Chr6:34-2Chr6:35\">2 أخبار الأيام 6:34–35</a>; <a href=\"https://ref.ly/2Chr20:5-2Chr20:7\">20:5–7</a>, <a href=\"https://ref.ly/2Chr20:20-2Chr20:24\">20–24</a>; <a href=\"https://ref.ly/Isa26:21-Isa27:6\">إشعياء 26:21–27:6</a>; <a href=\"https://ref.ly/Jonah3:4-Jonah3:10\">يونان 3:4–10</a>; <a href=\"https://ref.ly/Matt16:18\">متى 16:18</a>; <a href=\"https://ref.ly/2Cor10:3-2Cor10:6\">2 كورنثوس 10:3–6</a>; <a href=\"https://ref.ly/Eph1:19-Eph1:23\">أفسس 1:19–23</a>; <a href=\"https://ref.ly/Eph6:10-Eph6:20\">6:10–20</a>; <a href=\"https://ref.ly/Rev19:11-Rev19:21\">رؤيا 19:11–21</a></p>",
    "associations": {
      "passage": [
        {
          "start_ref": "14020003",
          "start_ref_usfm": "2CH 20:3",
          "end_ref": "14020003",
          "end_ref_usfm": "2CH 20:3"
        },
        {
          "start_ref": "14020018",
          "start_ref_usfm": "2CH 20:18",
          "end_ref": "14020018",
          "end_ref_usfm": "2CH 20:18"
        },
        {
          "start_ref": "14020021",
          "start_ref_usfm": "2CH 20:21",
          "end_ref": "14020021",
          "end_ref_usfm": "2CH 20:21"
        },
        {
          "start_ref": "40016018",
          "start_ref_usfm": "MAT 16:18",
          "end_ref": "40016018",
          "end_ref_usfm": "MAT 16:18"
        },
        {
          "start_ref": "66019006",
          "start_ref_usfm": "REV 19:6",
          "end_ref": "66019006",
          "end_ref_usfm": "REV 19:6"
        },
        {
          "start_ref": "49001019",
          "start_ref_usfm": "EPH 1:19",
          "end_ref": "49001023",
          "end_ref_usfm": "EPH 1:23"
        },
        {
          "start_ref": "49006010",
          "start_ref_usfm": "EPH 6:10",
          "end_ref": "49006020",
          "end_ref_usfm": "EPH 6:20"
        },
        {
          "start_ref": "66019011",
          "start_ref_usfm": "REV 19:11",
          "end_ref": "66019021",
          "end_ref_usfm": "REV 19:21"
        },
        {
          "start_ref": "66019011",
          "start_ref_usfm": "REV 19:11",
          "end_ref": "66020015",
          "end_ref_usfm": "REV 20:15"
        },
        {
          "start_ref": "46015024",
          "start_ref_usfm": "1CO 15:24",
          "end_ref": "46015028",
          "end_ref_usfm": "1CO 15:28"
        },
        {
          "start_ref": "14006034",
          "start_ref_usfm": "2CH 6:34",
          "end_ref": "14006035",
          "end_ref_usfm": "2CH 6:35"
        },
        {
          "start_ref": "14020020",
          "start_ref_usfm": "2CH 20:20",
          "end_ref": "14020024",
          "end_ref_usfm": "2CH 20:24"
        },
        {
          "start_ref": "14020005",
          "start_ref_usfm": "2CH 20:5",
          "end_ref": "14020012",
          "end_ref_usfm": "2CH 20:12"
        },
        {
          "start_ref": "14020022",
          "start_ref_usfm": "2CH 20:22",
          "end_ref": "14020024",
          "end_ref_usfm": "2CH 20:24"
        },
        {
          "start_ref": "49001019",
          "start_ref_usfm": "EPH 1:19",
          "end_ref": "49001021",
          "end_ref_usfm": "EPH 1:21"
        },
        {
          "start_ref": "06006001",
          "start_ref_usfm": "JOS 6:1",
          "end_ref": "06006020",
          "end_ref_usfm": "JOS 6:20"
        },
        {
          "start_ref": "06010007",
          "start_ref_usfm": "JOS 10:7",
          "end_ref": "06010015",
          "end_ref_usfm": "JOS 10:15"
        },
        {
          "start_ref": "07007007",
          "start_ref_usfm": "JDG 7:7",
          "end_ref": "07007022",
          "end_ref_usfm": "JDG 7:22"
        },
        {
          "start_ref": "12019014",
          "start_ref_usfm": "2KI 19:14",
          "end_ref": "12019037",
          "end_ref_usfm": "2KI 19:37"
        },
        {
          "start_ref": "14020005",
          "start_ref_usfm": "2CH 20:5",
          "end_ref": "14020007",
          "end_ref_usfm": "2CH 20:7"
        },
        {
          "start_ref": "23026021",
          "start_ref_usfm": "ISA 26:21",
          "end_ref": "23027006",
          "end_ref_usfm": "ISA 27:6"
        },
        {
          "start_ref": "32003004",
          "start_ref_usfm": "JON 3:4",
          "end_ref": "32003010",
          "end_ref_usfm": "JON 3:10"
        },
        {
          "start_ref": "47010003",
          "start_ref_usfm": "2CO 10:3",
          "end_ref": "47010006",
          "end_ref_usfm": "2CO 10:6"
        }
      ],
      "resource": []
    }
  }
]