[
  {
    "content_id": 764967,
    "reference_id": 203110,
    "title": "Kuteseka katika Kumfuata Mungu",
    "media_type": "Text",
    "index_reference": "kuteseka katika kumfuata mungu",
    "language": "swh",
    "content": "<p>Wakati mwingine, watu huhimiza wengine kumkubali Yesu Kristo kwa sababu wanaahidi kwamba atatatua matatizo yao. Hata hivyo, Yesu hakuahidi kutatua matatizo yote. Mara nyingi aliwaonya watu kufikiria gharama ya kumfuata (tazama, kwa mfano, <a href=\"https://ref.ly/Luke14:28\">Luka 14:28</a>). Pia alisisitiza ugumu ambao ungekuja kutokana na uamuzi wa kumfuata (tazama, kwa mfano, <a href=\"https://ref.ly/Mark8:34\">Marko 8:34</a>).</p><p><a href=\"https://ref.ly/Exod5:1-Exod5:23\">Kutoka 5</a> inatupa mfano wa jinsi kufuata Mungu wakati mwingine kunaweza kuleta changamoto zaidi mwanzoni. Hapo awali, Farao aliwafanya watu wa Kiebrania kuwa watumwa kwa sababu aliogopa walikuwa wakiongezeka sana na huenda wakasababisha matatizo kwa Misri (<a href=\"https://ref.ly/Exod1:8-Exod1:22\">1:8–22</a>). Katika sura ya <a href=\"https://ref.ly/Exod5:1-Exod5:23\">5</a>, hali inabadilika. Mose na Aroni walikuwa wamewapa watu matumaini kwa kuwaambia kwamba Mungu angewakomboa (<a href=\"https://ref.ly/Exod4:29-Exod4:31\">4:29–31</a>). Mose na Aroni walipokutana na Farao kwa mara ya kwanza, walimwambia kwamba Mungu ndiye mtawala wa kweli juu ya wote (<a href=\"https://ref.ly/Exod5:1-Exod5:3\">5:1–3</a>). Kama ilivyotarajiwa, Farao aliona hili kama changamoto kwa mamlaka yake kama mfalme, na alijibu kwa kufanya maisha kuwa magumu zaidi kwa Waisraeli (<a href=\"https://ref.ly/Exod5:4-Exod5:21\">5:4–21</a>).</p><p>Wakati ufalme wa Mungu unapopinga maadui wa Mungu, migogoro na mateso mara nyingi huwapata watu wa Mungu. Hili halipaswi kutushangaza. Mtu anapokuwa Mkristo, anaacha maisha yanayodhibitiwa na uovu na giza na kuanza maisha mapya yanayoongozwa na wema na mwanga wa Mungu (<a href=\"https://ref.ly/Col1:11-Col1:14\">Wakolosai 1:11–14</a>). Wale wanaotawala ufalme wa giza hawataturuhusu kuondoka bila mapambano. Lazima tusimame imara katika imani yetu, tukijua kwamba Mungu atatuhakikishia ushindi wa mwisho (<a href=\"https://ref.ly/Exod6:1-Exod6:8\">Kutoka 6:1–8</a>; tazama pia <a href=\"https://ref.ly/Matt5:11-Matt5:12\">Mathayo 5:11–12</a>; <a href=\"https://ref.ly/John16:33\">Yohana 16:33</a>; <a href=\"https://ref.ly/Rom16:20\">Warumi 16:20</a>; <a href=\"https://ref.ly/Eph6:10-Eph6:18\">Waefeso 6:10–18</a>).</p><p><u>Sehemu za Kujifunza Zaidi</u></p><p><a href=\"https://ref.ly/Gen39:6-Gen39:20\">Mwanzo 39:6–20</a>; <a href=\"https://ref.ly/Exod5:1-Exod5:23\">Kutoka 5:1–23</a>; <a href=\"https://ref.ly/Exod18:8\">18:8</a>; <a href=\"https://ref.ly/1Kgs18:3-1Kgs18:4\">1 Wafalme 18:3–4</a>; <a href=\"https://ref.ly/1Kgs19:1-1Kgs19:10\">19:1–10</a>; <a href=\"https://ref.ly/Ps6:6-Ps6:7\">Zaburi 6:6–7</a>; <a href=\"https://ref.ly/Ps22:11-Ps22:18\">22:11–18</a>; <a href=\"https://ref.ly/Matt5:11-Matt5:12\">Mathayo 5:11–12</a>; <a href=\"https://ref.ly/Mark8:34\">Marko 8:34</a>; <a href=\"https://ref.ly/John15:20\">Yohana 15:20</a>; <a href=\"https://ref.ly/John16:33\">16:33</a>; <a href=\"https://ref.ly/Rom16:20\">Warumi 16:20</a>; <a href=\"https://ref.ly/2Cor11:23-2Cor11:29\">2 Wakorintho 11:23–29</a>; <a href=\"https://ref.ly/Eph6:10-Eph6:18\">Waefeso 6:10–18</a>; <a href=\"https://ref.ly/2Tim3:12\">2 Timotheo 3:12</a>; <a href=\"https://ref.ly/Heb10:32-Heb10:36\">Waebrania 10:32–36</a>; <a href=\"https://ref.ly/1Pet1:6-1Pet1:7\">1 Petro 1:6–7</a>; <a href=\"https://ref.ly/1Pet3:9-1Pet3:17\">3:9–17</a>; <a href=\"https://ref.ly/1Pet4:12-1Pet4:19\">4:12–19</a></p>",
    "associations": {
      "passage": [
        {
          "start_ref": "02018008",
          "start_ref_usfm": "EXO 18:8",
          "end_ref": "02018008",
          "end_ref_usfm": "EXO 18:8"
        },
        {
          "start_ref": "41008034",
          "start_ref_usfm": "MRK 8:34",
          "end_ref": "41008034",
          "end_ref_usfm": "MRK 8:34"
        },
        {
          "start_ref": "42014028",
          "start_ref_usfm": "LUK 14:28",
          "end_ref": "42014028",
          "end_ref_usfm": "LUK 14:28"
        },
        {
          "start_ref": "43015020",
          "start_ref_usfm": "JHN 15:20",
          "end_ref": "43015020",
          "end_ref_usfm": "JHN 15:20"
        },
        {
          "start_ref": "43016033",
          "start_ref_usfm": "JHN 16:33",
          "end_ref": "43016033",
          "end_ref_usfm": "JHN 16:33"
        },
        {
          "start_ref": "45016020",
          "start_ref_usfm": "ROM 16:20",
          "end_ref": "45016020",
          "end_ref_usfm": "ROM 16:20"
        },
        {
          "start_ref": "55003012",
          "start_ref_usfm": "2TI 3:12",
          "end_ref": "55003012",
          "end_ref_usfm": "2TI 3:12"
        },
        {
          "start_ref": "02004029",
          "start_ref_usfm": "EXO 4:29",
          "end_ref": "02004031",
          "end_ref_usfm": "EXO 4:31"
        },
        {
          "start_ref": "02006001",
          "start_ref_usfm": "EXO 6:1",
          "end_ref": "02006008",
          "end_ref_usfm": "EXO 6:8"
        },
        {
          "start_ref": "02005001",
          "start_ref_usfm": "EXO 5:1",
          "end_ref": "02005003",
          "end_ref_usfm": "EXO 5:3"
        },
        {
          "start_ref": "11018003",
          "start_ref_usfm": "1KI 18:3",
          "end_ref": "11018004",
          "end_ref_usfm": "1KI 18:4"
        },
        {
          "start_ref": "58010032",
          "start_ref_usfm": "HEB 10:32",
          "end_ref": "58010036",
          "end_ref_usfm": "HEB 10:36"
        },
        {
          "start_ref": "40005011",
          "start_ref_usfm": "MAT 5:11",
          "end_ref": "40005012",
          "end_ref_usfm": "MAT 5:12"
        },
        {
          "start_ref": "60004012",
          "start_ref_usfm": "1PE 4:12",
          "end_ref": "60004019",
          "end_ref_usfm": "1PE 4:19"
        },
        {
          "start_ref": "60001006",
          "start_ref_usfm": "1PE 1:6",
          "end_ref": "60001007",
          "end_ref_usfm": "1PE 1:7"
        },
        {
          "start_ref": "19006006",
          "start_ref_usfm": "PSA 6:6",
          "end_ref": "19006007",
          "end_ref_usfm": "PSA 6:7"
        },
        {
          "start_ref": "49006010",
          "start_ref_usfm": "EPH 6:10",
          "end_ref": "49006018",
          "end_ref_usfm": "EPH 6:18"
        },
        {
          "start_ref": "02005001",
          "start_ref_usfm": "EXO 5:1",
          "end_ref": "02005023",
          "end_ref_usfm": "EXO 5:23"
        },
        {
          "start_ref": "02001008",
          "start_ref_usfm": "EXO 1:8",
          "end_ref": "02001022",
          "end_ref_usfm": "EXO 1:22"
        },
        {
          "start_ref": "02005004",
          "start_ref_usfm": "EXO 5:4",
          "end_ref": "02005021",
          "end_ref_usfm": "EXO 5:21"
        },
        {
          "start_ref": "51001011",
          "start_ref_usfm": "COL 1:11",
          "end_ref": "51001014",
          "end_ref_usfm": "COL 1:14"
        },
        {
          "start_ref": "01039006",
          "start_ref_usfm": "GEN 39:6",
          "end_ref": "01039020",
          "end_ref_usfm": "GEN 39:20"
        },
        {
          "start_ref": "11019001",
          "start_ref_usfm": "1KI 19:1",
          "end_ref": "11019010",
          "end_ref_usfm": "1KI 19:10"
        },
        {
          "start_ref": "19022011",
          "start_ref_usfm": "PSA 22:11",
          "end_ref": "19022018",
          "end_ref_usfm": "PSA 22:18"
        },
        {
          "start_ref": "47011023",
          "start_ref_usfm": "2CO 11:23",
          "end_ref": "47011029",
          "end_ref_usfm": "2CO 11:29"
        },
        {
          "start_ref": "60003009",
          "start_ref_usfm": "1PE 3:9",
          "end_ref": "60003017",
          "end_ref_usfm": "1PE 3:17"
        }
      ],
      "resource": []
    }
  }
]