[
  {
    "content_id": 700360,
    "reference_id": 203297,
    "title": "與耶穌相遇",
    "media_type": "Text",
    "index_reference": "與耶穌相遇",
    "language": "zht",
    "content": "<p>耶穌所行的神蹟與所講的比喻（具有特殊意義的象徵性故事）往往讓人把注意力轉移，忽略了祂與個別人相遇並改變他們生命的經歷。在這些相遇中，耶穌以他們的本相對待他們。祂邀請各種背景的人接受祂為領袖與朋友，並呼召他們成為祂永恆國度的跟隨者與使者。</p><p>然而，跟隨耶穌就需要作出選擇。世界的權勢與財富常常讓人分心，以致難以投入天國的事工。跟隨耶穌就意味著要捨棄某些東西。那些緊抓世俗事物不放的人，往往最終拒絕了耶穌。這個選擇對每一位在福音書中與耶穌相遇、並聽見祂呼召的人來說，都是一項挑戰。</p><p>安得烈是加利利的漁夫，他盼望彌賽亞（神所揀選的那一位）與祂的國度降臨。安得烈原是施洗約翰的門徒，直到約翰指認耶穌是那位彌賽亞，他便轉而跟隨耶穌，並邀請其他人（包括他的兄弟彼得）來跟從耶穌。<em>見</em><a href=\"https://ref.ly/John1:29-John1:42\"><em>約1:29–42</em></a>。</p><p>西面和亞拿素常等候那位所應許的基督。當他們見到嬰孩耶穌時，便認出祂就是基督。他們為祂的來到和祂所帶來的盼望稱頌神、感謝神。<em>見</em><a href=\"https://ref.ly/Luke2:25-Luke2:38\"><em>路2:25–38</em></a>。</p><p>拿但業起初受邀與耶穌見面時心存疑惑，然而當耶穌顯明祂早已認識拿但業時，他的態度就改變了。之後他毫不猶豫地跟從耶穌。<em>見</em><a href=\"https://ref.ly/John1:43-John1:51\"><em>約1:43–51</em></a>。</p><p>有一個財主來到耶穌面前，詢問如何才能承受永生。這人態度謙卑，並且一向謹守神的誡命。「耶穌……就愛他」，但告訴他要變賣他一切所有，分給窮人，並來跟從祂。那人不願捨棄財富，憂憂愁愁地離開了。<em>見</em><a href=\"https://ref.ly/Mark10:17-Mark10:22\"><em>可10:17–22</em></a>。</p><p>馬太背棄自己的猶太背景，成為羅馬的稅吏，背叛他的人民，選擇富足奢華的生活。當耶穌呼召馬太跟隨祂時，馬太便撇棄他舊有的生活方式。在與耶穌同行之前，他還邀請朋友來見耶穌。<em>見</em><a href=\"https://ref.ly/Matt9:9-Matt9:13\"><em>太9:9–13</em></a>。</p><p>當其他門徒說耶穌已經復活時，多馬並不相信他們的話。當耶穌向多馬顯現時，祂邀請多馬親手摸祂的釘痕。多馬便俯伏在耶穌面前，承認耶穌是他的主，是他的神。<em>見</em><a href=\"https://ref.ly/John20:19-John20:29\"><em>約20:19–29</em></a>。</p><p>馬大在家中忙著為耶穌預備飯食。由於妹妹馬利亞坐在耶穌腳前聽祂講道，馬大便心中不悅。耶穌溫柔地勸勉馬大不要焦躁，並指出馬利亞選擇了那更美的福分，就是聽祂的教導。後來，耶穌與馬大對話，堅固她對祂的信心，使她相信祂能賜人永生。<em>見</em><a href=\"https://ref.ly/Luke10:38-Luke10:42\"><em>路10:38–42</em></a><em>；</em><a href=\"https://ref.ly/John11:17-John11:27\"><em>約11:17–27</em></a>。</p><p>一位羅馬百夫長請求耶穌拯救他病重的僕人。因他是外邦人而不是猶太人，他認為自己的家在禮儀上不潔淨，便表示無需耶穌親自到家中。這是因為他相信，耶穌只要說一句話就能醫治人。耶穌因著這位百夫長的信心，從遠處醫治了那僕人，並稱讚他的信心，又宣告將有許多外邦人因信而進入天國。<em>見</em><a href=\"https://ref.ly/Matt8:5-Matt8:13\"><em>太8:5–13</em></a>。</p><p>一些猶太領袖帶了一名被指控犯姦淫的婦人到耶穌面前，要祂定她的罪。按照律法，她應被石頭打死。耶穌彎下身在地上寫字，並說凡沒有罪的人，就可以先拿石頭打她。當眾人都離開後，耶穌叫那婦人離開，從此不要再犯罪。<em>見</em><a href=\"https://ref.ly/John8:1-John8:11\"><em>約8:1–11</em></a>。</p><p>尼哥德慕是一位猶太的宗教領袖，也是法利賽人，因此他不願讓人看到自己與耶穌來往，便在夜間才去見耶穌。耶穌與他談話，挑戰他對屬靈真理的認識。後來，尼哥德慕在猶太議會（猶太公會）中為耶穌辯護。在耶穌被釘十字架之後，他又幫助埋葬耶穌，顯出他對耶穌的委身。<em>見</em><a href=\"https://ref.ly/John3:1-John3:21\"><em>約3:1–21</em></a><em>，</em><a href=\"https://ref.ly/John7:50-John7:52\"><em>7:50–52</em></a><em>，</em><a href=\"https://ref.ly/John19:38-John19:42\"><em>19:38–42</em></a>。</p><p>雅各和約翰認為神的國度近了，便請求在國度中得著尊貴的地位。這個請求讓其他門徒感到不滿。耶穌溫和地教導他們，真正的領導不是以財富或權勢為本，而是出於服事。門徒會在之後的艱難經歷中，學習到這一課。<em>見</em><a href=\"https://ref.ly/Mark10:35-Mark10:45\"><em>可10:35–45</em></a><em>；</em><a href=\"https://ref.ly/John13:1-John13:17\"><em>約13:1–17</em></a>。</p><p>拿撒勒的人只認識耶穌是約瑟的兒子，並不相信祂能成為基督。他們的懷疑大大限制了耶穌在他們中間所行的神蹟。當他們對耶穌的宣告感到忿怒時，耶穌便離開了那裡。<em>見</em><a href=\"https://ref.ly/Luke4:14-Luke4:30\"><em>路4:14–30</em></a>。</p><p>宗教領袖非常注重外在行為，遵守一切細節上的律法，卻在更重要的愛與憐憫上顯出虧欠。耶穌一再挑戰他們的虛假與驕傲，但大多數領袖拒絕祂的責備，反而設法加害於祂。<em>見</em><a href=\"https://ref.ly/Luke11:37-Luke11:54\"><em>路11:37–54</em></a><em>；參</em><a href=\"https://ref.ly/Acts6:8-Acts8:1\"><em>徒6:8–8:1，</em></a><em> </em><a href=\"https://ref.ly/Acts9:1-Acts9:31\"><em>9:1–31</em></a>。</p><p>撒該為羅馬徵收稅款，並藉著剝削百姓而致富。他想要見耶穌，就爬上一棵樹，好從人群中望見祂。耶穌注意到他，主動到他家中作客，並邀請他改變生命。撒該悔改，將自己不義得來的財富，償還給每個他曾虧欠的人。<em>見</em><a href=\"https://ref.ly/Luke19:1-Luke19:10\"><em>路19:1–10</em></a>。</p><p>耶穌受死後，有兩個門徒正回到以馬忤斯的家中。路上，復活的耶穌來到他們中間，用聖經解釋祂為何必須受死。他們起初未能認出耶穌，直到與祂一同吃飯時才認出祂來。那一刻，耶穌便從他們眼前消失了。他們立刻歡喜地回去，把耶穌復活的消息告訴其他門徒。<em>見</em><a href=\"https://ref.ly/Luke24:13-Luke24:35\"><em>路24:13–35</em></a>。</p><p>一位名聲欠佳的撒馬利亞婦人，到雅各井打水時遇見耶穌。耶穌向她應許「活水」與新的生命。她感到驚訝，卻相信了祂。隨後，她去邀請別人來見這位他們一直等候的基督。<em>見</em><a href=\"https://ref.ly/John4:1-John4:42\"><em>約4:1–42</em></a>。</p><p>猶太領袖向彼拉多施壓，要求處死耶穌。彼拉多知道耶穌是無辜的，並試圖釋放祂。彼拉多問耶穌：「真理是甚麼呢？」但他並不明白耶穌就是那真理。最後，彼拉多為了與猶太領袖妥協，維持局勢安穩，便下令將耶穌釘十字架。<em>見</em><a href=\"https://ref.ly/John18:28-John19:16\"><em>約18:28–19:16</em></a>。</p><p>西門彼得三次否認認識耶穌。耶穌復活之後，三次問彼得是否愛祂。彼得每次都回答說他愛祂。每次彼得都說他愛他。耶穌就吩咐他要牧養祂的跟隨者（祂的「羊」和「小羊」）。就這樣，耶穌恢復彼得，使他回到基督信仰的正路上。<em>見</em><a href=\"https://ref.ly/John21:1-John21:23\"><em>約21:1–23</em></a><em>；另見</em><a href=\"https://ref.ly/Matt16:15-Matt16:19\"><em>太16:15–19</em></a>。</p><p><u>進深研究的經文段落</u></p><p><a href=\"https://ref.ly/Matt8:5-Matt8:13\">太8:5–13，</a><a href=\"https://ref.ly/Matt9:9-Matt9:13\">9:9–13，</a><a href=\"https://ref.ly/Matt16:15-Matt16:19\">16:15–19</a>；<a href=\"https://ref.ly/Mark10:17-Mark10:22\">可10:17–22</a>，<a href=\"https://ref.ly/Mark10:35-Mark10:45\">35–45</a>；<a href=\"https://ref.ly/Luke2:25-Luke2:38\">路2:25–38，</a><a href=\"https://ref.ly/Luke4:14-Luke4:30\">4:14–30，</a><a href=\"https://ref.ly/Luke10:38-Luke10:42\">10:38–42，</a><a href=\"https://ref.ly/Luke11:37-Luke11:54\">11:37–54，</a><a href=\"https://ref.ly/Luke19:1-Luke19:10\">19:1–10，</a><a href=\"https://ref.ly/Luke24:13-Luke24:35\">24:13–35</a>；<a href=\"https://ref.ly/John1:29-John1:42\">約1:29–42</a>，<a href=\"https://ref.ly/John1:43-John1:51\">43–51，</a><a href=\"https://ref.ly/John3:1-John3:21\">3:1–21，</a><a href=\"https://ref.ly/John4:1-John4:42\">4:1–42，</a><a href=\"https://ref.ly/John7:50-John7:52\">7:50–52，</a><a href=\"https://ref.ly/John8:1-John8:11\">8:1–11，</a><a href=\"https://ref.ly/John11:17-John11:27\">11:17–27，</a><a href=\"https://ref.ly/John13:1-John13:17\">13:1–17，</a><a href=\"https://ref.ly/John18:28-John19:16\">18:28–19:16，</a><a href=\"https://ref.ly/John19:38-John19:42\">19:38–42，</a><a href=\"https://ref.ly/John20:19-John20:29\">20:19–29，</a><a href=\"https://ref.ly/John21:1-John21:23\">21:1–23</a></p>",
    "associations": {
      "passage": [
        {
          "start_ref": "42004014",
          "start_ref_usfm": "LUK 4:14",
          "end_ref": "42004030",
          "end_ref_usfm": "LUK 4:30"
        },
        {
          "start_ref": "40008005",
          "start_ref_usfm": "MAT 8:5",
          "end_ref": "40008013",
          "end_ref_usfm": "MAT 8:13"
        },
        {
          "start_ref": "43021001",
          "start_ref_usfm": "JHN 21:1",
          "end_ref": "43021023",
          "end_ref_usfm": "JHN 21:23"
        },
        {
          "start_ref": "41010035",
          "start_ref_usfm": "MRK 10:35",
          "end_ref": "41010045",
          "end_ref_usfm": "MRK 10:45"
        },
        {
          "start_ref": "43004001",
          "start_ref_usfm": "JHN 4:1",
          "end_ref": "43004042",
          "end_ref_usfm": "JHN 4:42"
        },
        {
          "start_ref": "42019001",
          "start_ref_usfm": "LUK 19:1",
          "end_ref": "42019010",
          "end_ref_usfm": "LUK 19:10"
        },
        {
          "start_ref": "43003001",
          "start_ref_usfm": "JHN 3:1",
          "end_ref": "43003021",
          "end_ref_usfm": "JHN 3:21"
        },
        {
          "start_ref": "43013001",
          "start_ref_usfm": "JHN 13:1",
          "end_ref": "43013017",
          "end_ref_usfm": "JHN 13:17"
        },
        {
          "start_ref": "43019038",
          "start_ref_usfm": "JHN 19:38",
          "end_ref": "43019042",
          "end_ref_usfm": "JHN 19:42"
        },
        {
          "start_ref": "40009009",
          "start_ref_usfm": "MAT 9:9",
          "end_ref": "40009013",
          "end_ref_usfm": "MAT 9:13"
        },
        {
          "start_ref": "42010038",
          "start_ref_usfm": "LUK 10:38",
          "end_ref": "42010042",
          "end_ref_usfm": "LUK 10:42"
        },
        {
          "start_ref": "41010017",
          "start_ref_usfm": "MRK 10:17",
          "end_ref": "41010022",
          "end_ref_usfm": "MRK 10:22"
        },
        {
          "start_ref": "43007050",
          "start_ref_usfm": "JHN 7:50",
          "end_ref": "43007052",
          "end_ref_usfm": "JHN 7:52"
        },
        {
          "start_ref": "42024013",
          "start_ref_usfm": "LUK 24:13",
          "end_ref": "42024035",
          "end_ref_usfm": "LUK 24:35"
        },
        {
          "start_ref": "43001043",
          "start_ref_usfm": "JHN 1:43",
          "end_ref": "43001051",
          "end_ref_usfm": "JHN 1:51"
        },
        {
          "start_ref": "43008001",
          "start_ref_usfm": "JHN 8:1",
          "end_ref": "43008011",
          "end_ref_usfm": "JHN 8:11"
        },
        {
          "start_ref": "42011037",
          "start_ref_usfm": "LUK 11:37",
          "end_ref": "42011054",
          "end_ref_usfm": "LUK 11:54"
        },
        {
          "start_ref": "44009001",
          "start_ref_usfm": "ACT 9:1",
          "end_ref": "44009031",
          "end_ref_usfm": "ACT 9:31"
        },
        {
          "start_ref": "43011017",
          "start_ref_usfm": "JHN 11:17",
          "end_ref": "43011027",
          "end_ref_usfm": "JHN 11:27"
        },
        {
          "start_ref": "42002025",
          "start_ref_usfm": "LUK 2:25",
          "end_ref": "42002038",
          "end_ref_usfm": "LUK 2:38"
        },
        {
          "start_ref": "43001029",
          "start_ref_usfm": "JHN 1:29",
          "end_ref": "43001042",
          "end_ref_usfm": "JHN 1:42"
        },
        {
          "start_ref": "43020019",
          "start_ref_usfm": "JHN 20:19",
          "end_ref": "43020029",
          "end_ref_usfm": "JHN 20:29"
        },
        {
          "start_ref": "44006008",
          "start_ref_usfm": "ACT 6:8",
          "end_ref": "44008001",
          "end_ref_usfm": "ACT 8:1"
        },
        {
          "start_ref": "43018028",
          "start_ref_usfm": "JHN 18:28",
          "end_ref": "43019016",
          "end_ref_usfm": "JHN 19:16"
        },
        {
          "start_ref": "40016015",
          "start_ref_usfm": "MAT 16:15",
          "end_ref": "40016019",
          "end_ref_usfm": "MAT 16:19"
        }
      ],
      "resource": []
    }
  }
]