[
  {
    "content_id": 700235,
    "reference_id": 203172,
    "title": "尋求耶和華",
    "media_type": "Text",
    "index_reference": "尋求耶和華",
    "language": "zht",
    "content": "<p>以色列人即將進入應許之地，摩西吩咐百姓要<span>求問</span>「<span>耶和華－你們的神從你們各支派中選擇何處為立他名的居所</span>」（<a href=\"https://ref.ly/Deut12:5\">申12:5</a>）。他提醒以色列人，要停止敬拜異教偶像，專心敬拜獨一的真神。在曠野中，他們建造了會幕，作為神<span>顯現衪</span>同在以及百姓敬拜祂的地方。當他們在應許之地定居後，摩西吩咐他們要為神建造一個永久的聖所。</p><p>在士師時期，以色列人時常敬拜鄰國的神明，而不是獨一的真神。王國時代開始時，人們曾盼望全國能合一地敬拜神；然而，第一位王<span>——</span>掃羅——<span>失去王位與性命，部分原因是他</span>「<span>求問交鬼的婦人</span>」 （<a href=\"https://ref.ly/1Chr10:13-1Chr10:14\">代上10:13–14</a>）。<span>以色列歷史上許多王跟掃羅一樣悖逆神，帶領國家</span>拜異教的偶像<span>。</span></p><p><span>與此形成鮮明對比的是大衛王，他被稱為</span>「<span>合他心意的人</span>」（<a href=\"https://ref.ly/1Sam13:14\">撒上13:14</a>）。他身為王的主要目標之一，就是恢復約櫃的<span>重要性，因這約櫃在掃羅年間被百姓忽視</span>（<a href=\"https://ref.ly/1Chr13:3\">代上13:3</a>）。</p><p>大衛初次嘗試運送約櫃至耶路撒冷，以失敗告終，因為他和利未人沒有求問耶和華該如何運送（<a href=\"https://ref.ly/1Chr13:1-1Chr13:14\">13:1–14</a>；<a href=\"https://ref.ly/1Chr15:13\">15:13</a>）。<span>後來大衛成功將約櫃迎入耶路撒冷</span>（<a href=\"https://ref.ly/1Chr15:1-1Chr16:1\">15:1–16:1</a>）。</p><p><span>耶路撒冷的聖所與敬拜，成為尋求耶和華的核心</span>。<span>當約櫃安放在耶路撒冷的帳幕後，大衛為利未人設立了音樂事奉的新職分</span>（<a href=\"https://ref.ly/1Chr16:4-1Chr16:6\">代上16:4–6</a>）。<span>在籌建聖殿期間，大衛常勸勉領袖「尋求耶和華－你們的神」</span>（<a href=\"https://ref.ly/1Chr22:19\">22:19</a>，參<a href=\"https://ref.ly/1Chr28:8-1Chr28:10\">28:8–10</a>）。</p><p>所羅門為鞏固國位所採取的第一個行動，就是召聚眾領袖到基遍的壇前，一同尋求耶和華（<a href=\"https://ref.ly/2Chr1:1-2Chr1:6\">代下1:1–6</a>）。耶和華在那裡向他顯現，賜給他無與倫比的智慧與財富。後來，所羅門完成聖殿的建造，並立定那殿為尋求耶和華的地方（<a href=\"https://ref.ly/2Chr6:1-2Chr6:42\">代下6</a>）。</p><p>先知以賽亞鼓勵那些等候神應許的人要尋求祂：「<span>當趁耶和華可尋找的時候尋找他， 相近的時候求告他</span>」（<a href=\"https://ref.ly/Isa55:6\">賽55:6</a>）。神的盟約與應許<span>必然實現</span>，<span>而且</span>是為尋求祂的人所預備的（<a href=\"https://ref.ly/Isa55:3\">55:3</a>）。</p><p><span><u>進深研究的經文段落</u></span></p><p><a href=\"https://ref.ly/1Chr10:13-1Chr10:14\">代上10:13–14</a>，<a href=\"https://ref.ly/1Chr13:3\">13:3</a>，<a href=\"https://ref.ly/1Chr16:11-1Chr16:13\">16:11–13</a>，<a href=\"https://ref.ly/1Chr22:19\">22:19</a>，<a href=\"https://ref.ly/1Chr28:8-1Chr28:10\">28:8–10</a>；<a href=\"https://ref.ly/2Chr6:19-2Chr6:40\">代下6:19–40</a>，<a href=\"https://ref.ly/2Chr7:14\">7:14</a>；<a href=\"https://ref.ly/Ps27:4-Ps27:8\">詩27:4–8</a>，<a href=\"https://ref.ly/Ps105:4-Ps105:6\">105:4–6</a>；<a href=\"https://ref.ly/Isa55:6-Isa55:7\">賽55:6–7</a>；<a href=\"https://ref.ly/Jer29:13-Jer29:14\">耶29:13–14</a>；<a href=\"https://ref.ly/Matt6:31-Matt6:33\">太6:31–33</a>；<a href=\"https://ref.ly/Rom2:7\">羅2:7</a></p>",
    "associations": {
      "passage": [
        {
          "start_ref": "05012005",
          "start_ref_usfm": "DEU 12:5",
          "end_ref": "05012005",
          "end_ref_usfm": "DEU 12:5"
        },
        {
          "start_ref": "09013014",
          "start_ref_usfm": "1SA 13:14",
          "end_ref": "09013014",
          "end_ref_usfm": "1SA 13:14"
        },
        {
          "start_ref": "13013003",
          "start_ref_usfm": "1CH 13:3",
          "end_ref": "13013003",
          "end_ref_usfm": "1CH 13:3"
        },
        {
          "start_ref": "13015013",
          "start_ref_usfm": "1CH 15:13",
          "end_ref": "13015013",
          "end_ref_usfm": "1CH 15:13"
        },
        {
          "start_ref": "13022019",
          "start_ref_usfm": "1CH 22:19",
          "end_ref": "13022019",
          "end_ref_usfm": "1CH 22:19"
        },
        {
          "start_ref": "14007014",
          "start_ref_usfm": "2CH 7:14",
          "end_ref": "14007014",
          "end_ref_usfm": "2CH 7:14"
        },
        {
          "start_ref": "23055003",
          "start_ref_usfm": "ISA 55:3",
          "end_ref": "23055003",
          "end_ref_usfm": "ISA 55:3"
        },
        {
          "start_ref": "23055006",
          "start_ref_usfm": "ISA 55:6",
          "end_ref": "23055006",
          "end_ref_usfm": "ISA 55:6"
        },
        {
          "start_ref": "45002007",
          "start_ref_usfm": "ROM 2:7",
          "end_ref": "45002007",
          "end_ref_usfm": "ROM 2:7"
        },
        {
          "start_ref": "13010013",
          "start_ref_usfm": "1CH 10:13",
          "end_ref": "13010014",
          "end_ref_usfm": "1CH 10:14"
        },
        {
          "start_ref": "23055006",
          "start_ref_usfm": "ISA 55:6",
          "end_ref": "23055007",
          "end_ref_usfm": "ISA 55:7"
        },
        {
          "start_ref": "13013001",
          "start_ref_usfm": "1CH 13:1",
          "end_ref": "13013014",
          "end_ref_usfm": "1CH 13:14"
        },
        {
          "start_ref": "13015001",
          "start_ref_usfm": "1CH 15:1",
          "end_ref": "13016001",
          "end_ref_usfm": "1CH 16:1"
        },
        {
          "start_ref": "13016004",
          "start_ref_usfm": "1CH 16:4",
          "end_ref": "13016006",
          "end_ref_usfm": "1CH 16:6"
        },
        {
          "start_ref": "13028008",
          "start_ref_usfm": "1CH 28:8",
          "end_ref": "13028010",
          "end_ref_usfm": "1CH 28:10"
        },
        {
          "start_ref": "14001001",
          "start_ref_usfm": "2CH 1:1",
          "end_ref": "14001006",
          "end_ref_usfm": "2CH 1:6"
        },
        {
          "start_ref": "14006001",
          "start_ref_usfm": "2CH 6:1",
          "end_ref": "14006042",
          "end_ref_usfm": "2CH 6:42"
        },
        {
          "start_ref": "13016011",
          "start_ref_usfm": "1CH 16:11",
          "end_ref": "13016013",
          "end_ref_usfm": "1CH 16:13"
        },
        {
          "start_ref": "14006019",
          "start_ref_usfm": "2CH 6:19",
          "end_ref": "14006040",
          "end_ref_usfm": "2CH 6:40"
        },
        {
          "start_ref": "19027004",
          "start_ref_usfm": "PSA 27:4",
          "end_ref": "19027008",
          "end_ref_usfm": "PSA 27:8"
        },
        {
          "start_ref": "19105004",
          "start_ref_usfm": "PSA 105:4",
          "end_ref": "19105006",
          "end_ref_usfm": "PSA 105:6"
        },
        {
          "start_ref": "24029013",
          "start_ref_usfm": "JER 29:13",
          "end_ref": "24029014",
          "end_ref_usfm": "JER 29:14"
        },
        {
          "start_ref": "40006031",
          "start_ref_usfm": "MAT 6:31",
          "end_ref": "40006033",
          "end_ref_usfm": "MAT 6:33"
        }
      ],
      "resource": []
    }
  }
]